midr/__init__.py
midr/main.py
midr-2.0.1.dist-info/licenses/LICENSE
midr-2.0.1.dist-info/METADATA
midr-2.0.1.dist-info/WHEEL
midr-2.0.1.dist-info/entry_points.txt
midr-2.0.1.dist-info/top_level.txt
midr-2.0.1.dist-info/RECORD
