Metadata-Version: 2.4
Name: midr
Version: 2.0.1
Summary: Compute the irreproducible discovery rate (IDR) for a given dataset.
License-Expression: AGPL-3.0-or-later
Project-URL: Homepage, https://gitbio.ens-lyon.fr/LBMC/physbio/idrpy
Classifier: Development Status :: 4 - Beta
Classifier: Operating System :: MacOS
Classifier: Operating System :: POSIX :: Linux
Classifier: Environment :: GPU
Classifier: Intended Audience :: Science/Research
Classifier: Topic :: Scientific/Engineering :: Information Analysis
Classifier: Topic :: Scientific/Engineering :: Bio-Informatics
Classifier: Programming Language :: Python :: 3
Classifier: Programming Language :: Python :: 3.12
Requires-Python: >=3.13
License-File: LICENSE
Requires-Dist: numpy>=2.2.3
Requires-Dist: polars-lts-cpu>=1.31.0
Requires-Dist: pyarrow>=19.0.1
Requires-Dist: rich-click>=1.8.9
Requires-Dist: torch>=2.6.0
Dynamic: license-file
